nwss/__init__.py
nwss/dump_to_jsonschema.py
nwss/fields.py
nwss/schemas.py
nwss/utils.py
nwss/validators.py
nwss/value_sets.py
nwss-1.0.1.dist-info/LICENSE
nwss-1.0.1.dist-info/METADATA
nwss-1.0.1.dist-info/WHEEL
nwss-1.0.1.dist-info/top_level.txt
nwss-1.0.1.dist-info/RECORD
