Metadata-Version: 2.1
Name: nwss
Version: 1.0.1
Summary: A marshmallow schema for the                 National Wastewater Surveillance System
Home-page: https://github.com/datamade/nwss-data-standard
Author: DataMade
Author-email: info@datamade.us
License: MIT
Keywords: National Wastewater Surveillance System,NWSS,DCIPHER,United States Center for Disease Control,COVID-19
Platform: any
Classifier: Intended Audience :: Developers
Classifier: License :: OSI Approved :: MIT License
Classifier: Operating System :: OS Independent
Classifier: Development Status :: 4 - Beta
Classifier: Programming Language :: Python :: 3.6
Classifier: Programming Language :: Python :: 3.7
Classifier: Programming Language :: Python :: 3.8
Classifier: Programming Language :: Python :: 3.9
Requires-Dist: marshmallow (>=3.11.1)
Requires-Dist: marshmallow-jsonschema (>=0.11.1)
Requires-Dist: jsonschema (>=3.2.0)
Provides-Extra: dev
Requires-Dist: pytest (>=3.6) ; extra == 'dev'
Requires-Dist: flake8 ; extra == 'dev'
